{
    "SourceToTargetID": 1,
    "SourceSystemCode": "AW",
    "SourceSystemName": "AdventureWorks",
    "PipelineID": 1,
    "PipelineName": "BronseToSilver",
    "FlowID": 1,
    "FlowName": "SalesLTAddress",
    "NotebookName": "DataProcessing",
    "SourceStorageAccount": "storageincoming001",
    "SourceContainer": "container01",
    "SourcePath": "/landingzone/AdventureWorks/",
    "SourceFileType": "CSV",
    "TargetStorageAccount": "storageoutgoing001",
    "TargetContainer": "container02",
    "TargetPath": "/processedzone/AdventureWorks",
    "TargetFileType": "DELTA",
    "SinkOperation": "Merge",
    "PrimaryKey": "AddressID",
    "BusinessKey": "AddressID",
    "PipelineDescription": "Transform CSVs to Delta files" 
}